Experiment-2-Beginner/RTL/cfar_core.v
`timescale 1ns / 1ps
// Streaming CA-CFAR on unsigned linear-domain magnitudes or powers.
// 8 training, 2 guard, CUT, 2 guard, 8 training (21 accepted samples).
// scale_shift = 0/1/2/3 means alpha = 1/2/4/8.
// threshold = floor(sum(training)/16) * alpha; strict CUT > threshold.
// After accepting sample n >= 20, result for CUT n-10 appears TWO
// clock periods later. Stalls do not advance the sample window.
module cfar_core (
    input wire clk, input wire reset,
    input wire [15:0] data_in, input wire data_valid,
    input wire [1:0] scale_shift,
    output reg result_valid, output reg target_detected,
    output reg [15:0] threshold_value,
    output reg [18:0] threshold_full,
    output reg [15:0] cut_value, output reg [15:0] cut_index
);
    reg [15:0] window_data [0:20];
    reg [4:0] fill_count;
    reg [15:0] input_index;
    reg [17:0] p0, p1, p2, p3;
    reg [15:0] cut_s1, index_s1, cut_s2, index_s2;
    reg [1:0] scale_s1, scale_s2;
    reg valid_s1, valid_s2;
    reg [19:0] sum_s2;
    wire [18:0] threshold_comb = {3'b000, sum_s2[19:4]} << scale_s2;
    integer i;

    always @(posedge clk) begin
        if (reset) begin
            for (i = 0; i < 21; i = i + 1) window_data[i] <= 16'd0;
            fill_count <= 0; input_index <= 0;
            p0 <= 0; p1 <= 0; p2 <= 0; p3 <= 0;
            cut_s1 <= 0; index_s1 <= 0; scale_s1 <= 0;
            cut_s2 <= 0; index_s2 <= 0; scale_s2 <= 0; sum_s2 <= 0;
            valid_s1 <= 0; valid_s2 <= 0; result_valid <= 0;
            target_detected <= 0; threshold_value <= 0;
            threshold_full <= 0; cut_value <= 0; cut_index <= 0;
        end else begin
            // Stage 1: partial sums of the NEW window, including this input.
            valid_s1 <= data_valid && (fill_count >= 20);
            if (data_valid) begin
                window_data[0] <= data_in;
                for (i = 1; i < 21; i = i + 1)
                    window_data[i] <= window_data[i-1];
                if (fill_count < 21) fill_count <= fill_count + 1'b1;
                input_index <= input_index + 1'b1;
                if (fill_count >= 20) begin
                    p0 <= {2'b00, data_in} + {2'b00, window_data[0]}
                        + {2'b00, window_data[1]} + {2'b00, window_data[2]};
                    p1 <= {2'b00, window_data[3]} + {2'b00, window_data[4]}
                        + {2'b00, window_data[5]} + {2'b00, window_data[6]};
                    p2 <= {2'b00, window_data[12]} + {2'b00, window_data[13]}
                        + {2'b00, window_data[14]} + {2'b00, window_data[15]};
                    p3 <= {2'b00, window_data[16]} + {2'b00, window_data[17]}
                        + {2'b00, window_data[18]} + {2'b00, window_data[19]};
                    cut_s1 <= window_data[9];
                    index_s1 <= input_index - 16'd10;
                    scale_s1 <= scale_shift;
                end
            end
            // Stage 2: full-width total and matching metadata.
            valid_s2 <= valid_s1;
            if (valid_s1) begin
                sum_s2 <= ({2'b00, p0} + {2'b00, p1})
                        + ({2'b00, p2} + {2'b00, p3});
                cut_s2 <= cut_s1; index_s2 <= index_s1; scale_s2 <= scale_s1;
            end
            // Stage 3: full-width comparison; only the display is saturated.
            result_valid <= valid_s2;
            target_detected <= 1'b0;
            if (valid_s2) begin
                threshold_full <= threshold_comb;
                threshold_value <= (threshold_comb > 19'd65535)
                                 ? 16'hffff : threshold_comb[15:0];
                target_detected <= ({3'b000, cut_s2} > threshold_comb);
                cut_value <= cut_s2; cut_index <= index_s2;
            end
        end
    end
endmodule

Experiment-2-Beginner/RTL/radar_demo.v
`timescale 1ns / 1ps
// Standalone controller: generate 100 samples, drain ALL 80 full windows,
// capture stable results. No software sample timing or AXI transaction needed.
module radar_demo (
    input wire clk, input wire reset, input wire start,
    input wire [1:0] scenario, input wire [1:0] scale_shift,
    input wire gap_mode,
    output wire busy, output reg done, output reg timeout_error,
    output reg [7:0] detection_count,
    output reg [15:0] result_count,
    output reg [15:0] target_pos0, target_pos1, target_pos2,
    output reg [127:0] detection_mask,
    output reg [15:0] last_threshold,
    output reg [18:0] last_threshold_full,
    output reg [15:0] run_cycles, output reg [15:0] frame_id,
    output reg [1:0] active_scenario, active_scale,
    output reg active_gap
);
    localparam IDLE = 2'd0, CLEAR = 2'd1, FEED = 2'd2, DRAIN = 2'd3;
    reg [1:0] state;
    reg start_d;
    reg [6:0] sample_index;
    reg [1:0] gap_count;
    wire send_sample = (state == FEED) && (gap_count == 0);
    wire core_reset = reset || (state == CLEAR);
    wire result_valid, detected;
    wire [15:0] threshold, cut_value, cut_index;
    wire [18:0] full_threshold;
    reg [15:0] sample_value;
    assign busy = (state != IDLE);

    always @* begin
        sample_value = (active_scenario == 3) ? 16'd20000 : 16'd100;
        case (active_scenario)
            1: case (sample_index)
                30: sample_value = 16'd1000;
                60: sample_value = 16'd1200;
                85: sample_value = 16'd900;
                default: ;
            endcase
            2: if (sample_index == 30) sample_value = 16'd300;
            3: if (sample_index == 30) sample_value = 16'd60000;
            default: ;
        endcase
    end

    cfar_core u_core (
        .clk(clk), .reset(core_reset), .data_in(sample_value),
        .data_valid(send_sample), .scale_shift(active_scale),
        .result_valid(result_valid), .target_detected(detected),
        .threshold_value(threshold), .threshold_full(full_threshold),
        .cut_value(cut_value), .cut_index(cut_index)
    );

    always @(posedge clk) begin
        if (reset) begin
            state <= IDLE; start_d <= 0; sample_index <= 0; gap_count <= 0;
            done <= 0; timeout_error <= 0; detection_count <= 0;
            result_count <= 0; target_pos0 <= 16'hffff;
            target_pos1 <= 16'hffff; target_pos2 <= 16'hffff;
            detection_mask <= 0; last_threshold <= 0; last_threshold_full <= 0;
            run_cycles <= 0; frame_id <= 0;
            active_scenario <= 0; active_scale <= 2; active_gap <= 0;
        end else begin
            start_d <= start;
            if (busy) run_cycles <= run_cycles + 1'b1;
            case (state)
                IDLE: if (start && !start_d) begin
                    active_scenario <= scenario;
                    active_scale <= scale_shift; active_gap <= gap_mode;
                    frame_id <= frame_id + 1'b1;
                    done <= 0; timeout_error <= 0; detection_count <= 0;
                    result_count <= 0; detection_mask <= 0;
                    target_pos0 <= 16'hffff; target_pos1 <= 16'hffff;
                    target_pos2 <= 16'hffff;
                    last_threshold <= 0; last_threshold_full <= 0;
                    sample_index <= 0; gap_count <= 0; run_cycles <= 0;
                    state <= CLEAR;
                end
                CLEAR: state <= FEED;
                FEED: begin
                    if (send_sample) begin
                        if (sample_index == 99) state <= DRAIN;
                        else sample_index <= sample_index + 1'b1;
                        gap_count <= active_gap ? 2'd2 : 2'd0;
                    end else gap_count <= gap_count - 1'b1;
                end
                DRAIN: if (result_valid && result_count == 79) begin
                    state <= IDLE; done <= 1'b1;
                end
                default: state <= IDLE;
            endcase
            if (busy && result_valid) begin
                result_count <= result_count + 1'b1;
                last_threshold <= threshold;
                last_threshold_full <= full_threshold;
                if (detected) begin
                    if (cut_index < 128) detection_mask[cut_index] <= 1'b1;
                    case (detection_count)
                        0: target_pos0 <= cut_index;
                        1: target_pos1 <= cut_index;
                        2: target_pos2 <= cut_index;
                        default: ;
                    endcase
                    detection_count <= detection_count + 1'b1;
                end
            end
            if (busy && run_cycles >= 1023) begin
                timeout_error <= 1'b1; state <= IDLE; done <= 1'b1;
            end
        end
    end
endmodule

Experiment-2-Beginner/Testbench/tb_radar_demo.sv
`timescale 1ns / 1ps
module tb_radar_demo;
    reg clk=0;always #10 clk=~clk;
    reg reset=1,start=0,gap_mode=0;
    reg [1:0] scenario=0,scale_shift=2;
    wire busy,done,timeout_error;
    wire [7:0] detection_count;
    wire [15:0] result_count,target_pos0,target_pos1,target_pos2;
    wire [127:0] detection_mask;
    wire [15:0] last_threshold,run_cycles,frame_id;
    wire [18:0] last_threshold_full;
    wire [1:0] active_scenario,active_scale;
    wire active_gap;
    radar_demo dut(.*);
    integer tests=0,fd,cycles,i,j,g;
    reg [15:0] old_id;
    reg [127:0] expected_mask;
    string outdir=".";
    task run_case(input integer sc,input integer a,input integer gap);
        integer count_expected;
        begin
            @(negedge clk);start=0;scenario=sc;scale_shift=a;gap_mode=gap;
            old_id=frame_id;
            @(negedge clk);start=1;
            @(negedge clk);start=0;
            // While busy, altered live controls must not alter a latched frame.
            scenario=0;scale_shift=0;gap_mode=0;
            cycles=0;
            while((!done || frame_id==old_id) && cycles<1100) begin
                @(negedge clk);cycles=cycles+1;
            end
            if(!done||busy||timeout_error||result_count!=80||frame_id!=old_id+1)
                $fatal(1,"Frame completion failed sc=%0d a=%0d gap=%0d",sc,a,gap);
            if(active_scenario!=sc||active_scale!=a||active_gap!=gap)
                $fatal(1,"Latched controls mismatch");
            expected_mask=0;
            if(sc==1) expected_mask=(128'b1<<30)|(128'b1<<60)|(128'b1<<85);
            if(sc==2 && a<=1) expected_mask=128'b1<<30;
            if(sc==3 && a<=1) expected_mask=128'b1<<30;
            count_expected=(sc==1)?3:((expected_mask!=0)?1:0);
            if(detection_count!=count_expected || detection_mask!==expected_mask)
                $fatal(1,"Detection mismatch sc=%0d a=%0d got=%0d",sc,a,detection_count);
            if(target_pos0!=((count_expected>0)?30:65535)||
               target_pos1!=((count_expected==3)?60:65535)||
               target_pos2!=((count_expected==3)?85:65535)) $fatal(1,"Position mismatch");
            if(last_threshold_full!=((sc==3)?20000:(sc==1)?150:100)*(1<<a) ||
               last_threshold!=((((sc==3)?20000:(sc==1)?150:100)*(1<<a)>65535)?65535:((sc==3)?20000:(sc==1)?150:100)*(1<<a)))
                $fatal(1,"Final threshold mismatch");
            if(run_cycles!=((gap==0)?104:302))
                $fatal(1,"Cycle count mismatch got=%0d gap=%0d",run_cycles,gap);
            tests=tests+1;
            $display("DEMO PASS sc=%0d alpha=%0d gap=%0d detections=%0d results=%0d cycles=%0d",
                sc,1<<a,gap,detection_count,result_count,run_cycles);
            // Results and done must remain stable while idle.
            repeat(8) @(negedge clk);
            if(!done||result_count!=80||detection_mask!==expected_mask)$fatal(1,"Results not retained");
        end
    endtask
    initial begin
        if($value$plusargs("OUTDIR=%s",outdir)) begin end
`ifdef __ICARUS__
        $dumpfile("Simulation/radar_demo.vcd");$dumpvars(0,tb_radar_demo);
`endif
        repeat(4) @(negedge clk); reset=0;
        for(i=0;i<4;i=i+1)for(j=0;j<4;j=j+1)for(g=0;g<2;g=g+1)run_case(i,j,g);
        // Held start causes one frame only.
        @(negedge clk);start=1;scenario=1;scale_shift=2;old_id=frame_id;
        repeat(150) @(negedge clk);
        if(!done||frame_id!=old_id+1)$fatal(1,"Held start repeats a frame");
        @(negedge clk);start=0;
        // An active frame can be reset, followed by a clean repeat.
        @(negedge clk);start=1;
        repeat(30) @(negedge clk);reset=1;start=0;
        repeat(3) @(negedge clk);reset=0;
        if(busy||done||frame_id!=0||result_count!=0)$fatal(1,"Reset failed");
        run_case(1,2,0);
        fd=$fopen({outdir,"/Results/tb_radar_demo_PASS.txt"},"w");
        if(!fd)$fatal(1,"Cannot write PASS marker");
        $fdisplay(fd,"PASS frame_checks=%0d plus held-start and active-reset",tests);$fclose(fd);
        $display("DEMO SIMULATION PASS: %0d frame checks",tests);$finish;
    end
    initial begin #500000;$fatal(1,"Demo watchdog timeout");end
endmodule

Experiment-2-Beginner/Simulation/radar_demo.vcd
$date
	Fri Oct  9 01:05:13 2026
$end
$version
	Icarus Verilog
$end
$timescale
	1ps
$end
$scope module tb_radar_demo $end
$var wire 1 ! timeout_error $end
$var wire 16 " target_pos2 [15:0] $end
$var wire 16 # target_pos1 [15:0] $end
$var wire 16 $ target_pos0 [15:0] $end
$var wire 16 % run_cycles [15:0] $end
$var wire 16 & result_count [15:0] $end
$var wire 19 ' last_threshold_full [18:0] $end
$var wire 16 ( last_threshold [15:0] $end
$var wire 16 ) frame_id [15:0] $end
$var wire 1 * done $end
$var wire 128 + detection_mask [127:0] $end
$var wire 8 , detection_count [7:0] $end
$var wire 1 - busy $end
$var wire 2 . active_scenario [1:0] $end
$var wire 2 / active_scale [1:0] $end
$var wire 1 0 active_gap $end
$var reg 1 1 clk $end
$var reg 128 2 expected_mask [127:0] $end
$var reg 1 3 gap_mode $end
$var reg 16 4 old_id [15:0] $end
$var reg 1 5 reset $end
$var reg 2 6 scale_shift [1:0] $end
$var reg 2 7 scenario [1:0] $end
$var reg 1 8 start $end
$var integer 32 9 cycles [31:0] $end
$var integer 32 : fd [31:0] $end
$var integer 32 ; g [31:0] $end
$var integer 32 < i [31:0] $end
$var integer 32 = j [31:0] $end
$var integer 32 > tests [31:0] $end
$scope module dut $end
$var wire 1 1 clk $end
$var wire 1 ? core_reset $end
$var wire 1 3 gap_mode $end
$var wire 1 5 reset $end
$var wire 2 @ scale_shift [1:0] $end
$var wire 2 A scenario [1:0] $end
$var wire 1 B send_sample $end
$var wire 1 8 start $end
$var wire 16 C threshold [15:0] $end
$var wire 1 D result_valid $end
$var wire 19 E full_threshold [18:0] $end
$var wire 1 F detected $end
$var wire 16 G cut_value [15:0] $end
$var wire 16 H cut_index [15:0] $end
$var wire 1 - busy $end
$var parameter 2 I CLEAR $end
$var parameter 2 J DRAIN $end
$var parameter 2 K FEED $end
$var parameter 2 L IDLE $end
$var reg 1 0 active_gap $end
$var reg 2 M active_scale [1:0] $end
$var reg 2 N active_scenario [1:0] $end
$var reg 8 O detection_count [7:0] $end
$var reg 128 P detection_mask [127:0] $end
$var reg 1 * done $end
$var reg 16 Q frame_id [15:0] $end
$var reg 2 R gap_count [1:0] $end
$var reg 16 S last_threshold [15:0] $end
$var reg 19 T last_threshold_full [18:0] $end
$var reg 16 U result_count [15:0] $end
$var reg 16 V run_cycles [15:0] $end
$var reg 7 W sample_index [6:0] $end
$var reg 16 X sample_value [15:0] $end
$var reg 1 Y start_d $end
$var reg 2 Z state [1:0] $end
$var reg 16 [ target_pos0 [15:0] $end
$var reg 16 \ target_pos1 [15:0] $end
$var reg 16 ] target_pos2 [15:0] $end
$var reg 1 ! timeout_error $end
$scope module u_core $end
$var wire 1 1 clk $end
$var wire 16 ^ data_in [15:0] $end
$var wire 1 B data_valid $end
$var wire 1 ? reset $end
$var wire 2 _ scale_shift [1:0] $end
$var wire 19 ` threshold_comb [18:0] $end
$var reg 16 a cut_index [15:0] $end
$var reg 16 b cut_s1 [15:0] $end
$var reg 16 c cut_s2 [15:0] $end
$var reg 16 d cut_value [15:0] $end
$var reg 5 e fill_count [4:0] $end
$var reg 16 f index_s1 [15:0] $end
$var reg 16 g index_s2 [15:0] $end
$var reg 16 h input_index [15:0] $end
$var reg 18 i p0 [17:0] $end
$var reg 18 j p1 [17:0] $end
$var reg 18 k p2 [17:0] $end
$var reg 18 l p3 [17:0] $end
$var reg 1 D result_valid $end
$var reg 2 m scale_s1 [1:0] $end
$var reg 2 n scale_s2 [1:0] $end
$var reg 20 o sum_s2 [19:0] $end
$var reg 1 F target_detected $end
$var reg 19 p threshold_full [18:0] $end
$var reg 16 q threshold_value [15:0] $end
$var reg 1 r valid_s1 $end
$var reg 1 s valid_s2 $end
$var integer 32 t i [31:0] $end
$upscope $end
$upscope $end
$scope task run_case $end
$var integer 32 u a [31:0] $end
$var integer 32 v count_expected [31:0] $end
$var integer 32 w gap [31:0] $end
$var integer 32 x sc [31:0] $end
$upscope $end
$upscope $end
$enddefinitions $end
$comment Show the parameter values. $end
$dumpall
b0 L
b10 K
b11 J
b1 I
$end
#0
$dumpvars
bx x
bx w
bx v
bx u
bx t
xs
xr
bx q
bx p
bx o
bx n
bx m
bx l
bx k
bx j
bx i
bx h
bx g
bx f
bx e
bx d
bx c
bx b
bx a
bx `
bx _
bx ^
bx ]
bx \
bx [
bx Z
xY
bx X
bx W
bx V
bx U
bx T
bx S
bx R
bx Q
bx P
bx O
bx N
bx M
bx H
bx G
xF
bx E
xD
bx C
xB
b0 A
b10 @
1?
b0 >
bx =
bx <
bx ;
bx :
bx 9
08
b0 7
b10 6
15
bx 4
03
bx 2
01
x0
bx /
bx .
x-
bx ,
bx +
x*
bx )
bx (
bx '
bx &
bx %
bx $
bx #
bx "
x!
$end
#10000
b1100100 X
b1100100 ^
0B
b0 H
b0 a
b0 G
b0 d
b0 E
b0 p
b0 C
b0 q
0F
0D
0s
0r
b0 o
b0 `
b0 n
b0 g
b0 c
b0 m
b0 f
b0 b
b0 l
b0 k
b0 j
b0 i
b0 h
b0 e
00
b10 /
b10 M
b10 _
b0 .
b0 N
b0 )
b0 Q
b0 %
b0 V
b0 '
b0 T
b0 (
b0 S
b0 +
b0 P
b1111111111111111 "
b1111111111111111 ]
b1111111111111111 #
b1111111111111111 \
b1111111111111111 $
b1111111111111111 [
b0 &
b0 U
b0 ,
b0 O
0!
0*
b0 R
b0 W
0Y
0-
b0 Z
b10101 t
11
#20000
01
#30000
b10101 t
11
#40000
01
#50000
b10101 t
11
#60000
01
#70000
b10101 t
11
#80000
0?
b0 w
b0 u
b0 x
b0 ;
b0 =
b0 <
05
01
#90000
11
#100000
b0 4
b0 6
b0 @
01
#110000
11
#120000
18
01
#130000
1?
1-
b1 Z
b1 )
b1 Q
b0 /
b0 M
b0 _
1Y
11
#140000
b0 9
08
01
#150000
1B
0?
b10 Z
b1 %
b1 V
0Y
b10101 t
11
#160000
b1 9
01
#170000
b1 h
b1 e
b1 W
b10 %
b10 V
b10101 t
11
#180000
b10 9
01
#190000
b10 W
b11 %
b11 V
b10 h
b10 e
b10101 t
11
#200000
b11 9
01
#210000
b11 h
b11 e
b11 W
b100 %
b100 V
b10101 t
11
#220000
b100 9
01
#230000
b100 W
b101 %
b101 V
b100 h
b100 e
b10101 t
11
#240000
b101 9
01
#250000
b101 h
b101 e
b101 W
b110 %
b110 V
b10101 t
11
#260000
b110 9
01
#270000
b110 W
b111 %
b111 V
b110 h
b110 e
b10101 t
11
#280000
b111 9
01
#290000
b111 h
b111 e
b111 W
b1000 %
b1000 V
b10101 t
11
#300000
b1000 9
01
#310000
b1000 W
b1001 %
b1001 V
b1000 h
b1000 e
b10101 t
11
#320000
b1001 9
01
#330000
b1001 h
b1001 e
b1001 W
b1010 %
b1010 V
b10101 t
11
#340000
b1010 9
01
#350000
b1010 W
b1011 %
b1011 V
b1010 h
b1010 e
b10101 t
11
#360000
b1011 9
01
#370000
b1011 h
b1011 e
b1011 W
b1100 %
b1100 V
b10101 t
11
#380000
b1100 9
01
#390000
b1100 W
b1101 %
b1101 V
b1100 h
b1100 e
b10101 t
11
#400000
b1101 9
01
#410000
b1101 h
b1101 e
b1101 W
b1110 %
b1110 V
b10101 t
11
#420000
b1110 9
01
#430000
b1110 W
b1111 %
b1111 V
b1110 h
b1110 e
b10101 t
11
#440000
b1111 9
01
#450000
b1111 h
b1111 e
b1111 W
b10000 %
b10000 V
b10101 t
11
#460000
b10000 9
01
#470000
b10000 W
b10001 %
b10001 V
b10000 h
b10000 e
b10101 t
11
#480000
b10001 9
01
#490000
b10001 h
b10001 e
b10001 W
b10010 %
b10010 V
b10101 t
11
#500000
b10010 9
01
#510000
b10010 W
b10011 %
b10011 V
b10010 h
b10010 e
b10101 t
11
#520000
b10011 9
01
#530000
b10011 h
b10011 e
b10011 W
b10100 %
b10100 V
b10101 t
11
#540000
b10100 9
01
#550000
b10100 W
b10101 %
b10101 V
b10100 h
b10100 e
b10101 t
11
#560000
b10101 9
01
#570000
b1010 f
b1100100 b
b110010000 l
b110010000 k
b110010000 j
b110010000 i
b10101 h
b10101 e
1r
b10101 W
b10110 %
b10110 V
b10101 t
11
#580000
b10110 9
01
#590000
b1100100 `
b10110 W
b10111 %
b10111 V
b1010 g
b1100100 c
b11001000000 o
1s
b1011 f
b10110 h
b10101 t
11
#600000
b10111 9
01
#610000
b1010 H
b1010 a
b1100100 G
b1100100 d
b1100100 C
b1100100 q
b1100100 E
b1100100 p
1D
b1011 g
b1100 f
b10111 h
b10111 W
b11000 %
b11000 V
b10101 t
11
#620000
b11000 9
01
#630000
b1100100 '
b1100100 T
b1100100 (
b1100100 S
b1 &
b1 U
b11000 W
b11001 %
b11001 V
b1011 H
b1011 a
b1100 g
b1101 f
b11000 h
b10101 t
11
#640000
b11001 9
01
#650000
b1100 H
b1100 a
b1101 g
b1110 f
b11001 h
b10 &
b10 U
b11001 W
b11010 %
b11010 V
b10101 t
11
#660000
b11010 9
01
#670000
b11 &
b11 U
b11010 W
b11011 %
b11011 V
b1101 H
b1101 a
b1110 g
b1111 f
b11010 h
b10101 t
11
#680000
b11011 9
01
#690000
b1110 H
b1110 a
b1111 g
b10000 f
b11011 h
b100 &
b100 U
b11011 W
b11100 %
b11100 V
b10101 t
11
#700000
b11100 9
01
#710000
b101 &
b101 U
b11100 W
b11101 %
b11101 V
b1111 H
b1111 a
b10000 g
b10001 f
b11100 h
b10101 t
11
#720000
b11101 9
01
#730000
b10000 H
b10000 a
b10001 g
b10010 f
b11101 h
b110 &
b110 U
b11101 W
b11110 %
b11110 V
b10101 t
11
#740000
b11110 9
01
#750000
b111 &
b111 U
b11110 W
b11111 %
b11111 V
b10001 H
b10001 a
b10010 g
b10011 f
b11110 h
b10101 t
11
#760000
b11111 9
01
#770000
b10010 H
b10010 a
b10011 g
b10100 f
b11111 h
b1000 &
b1000 U
b11111 W
b100000 %
b100000 V
b10101 t
11
#780000
b100000 9
01
#790000
b1001 &
b1001 U
b100000 W
b100001 %
b100001 V
b10011 H
b10011 a
b10100 g
b10101 f
b100000 h
b10101 t
11
#800000
b100001 9
01
#810000
b10100 H
b10100 a
b10101 g
b10110 f
b100001 h
b1010 &
b1010 U
b100001 W
b100010 %
b100010 V
b10101 t
11
#820000
b100010 9
01
#830000
b1011 &
b1011 U
b100010 W
b100011 %
b100011 V
b10101 H
b10101 a
b10110 g
b10111 f
b100010 h
b10101 t
11
#840000
b100011 9
01
#850000
b10110 H
b10110 a
b10111 g
b11000 f
b100011 h
b1100 &
b1100 U
b100011 W
b100100 %
b100100 V
b10101 t
11
#860000
b100100 9
01
#870000
b1101 &
b1101 U
b100100 W
b100101 %
b100101 V
b10111 H
b10111 a
b11000 g
b11001 f
b100100 h
b10101 t
11
#880000
b100101 9
01
#890000
b11000 H
b11000 a
b11001 g
b11010 f
b100101 h
b1110 &
b1110 U
b100101 W
b100110 %
b100110 V
b10101 t
11
#900000
b100110 9
01
#910000
b1111 &
b1111 U
b100110 W
b100111 %
b100111 V
b11001 H
b11001 a
b11010 g
b11011 f
b100110 h
b10101 t
11
#920000
b100111 9
01
#930000
b11010 H
b11010 a
b11011 g
b11100 f
b100111 h
b10000 &
b10000 U
b100111 W
b101000 %
b101000 V
b10101 t
11
#940000
b101000 9
01
#950000
b10001 &
b10001 U
b101000 W
b101001 %
b101001 V
b11011 H
b11011 a
b11100 g
b11101 f
b101000 h
b10101 t
11
#960000
b101001 9
01
#970000
b11100 H
b11100 a
b11101 g
b11110 f
b101001 h
b10010 &
b10010 U
b101001 W
b101010 %
b101010 V
b10101 t
11
#980000
b101010 9
01
#990000
b10011 &
b10011 U
b101010 W
b101011 %
b101011 V
b11101 H
b11101 a
b11110 g
b11111 f
b101010 h
b10101 t
11
#1000000
b101011 9
01
#1010000
b11110 H
b11110 a
b11111 g
b100000 f
b101011 h
b10100 &
b10100 U
b101011 W
b101100 %
b101100 V
b10101 t
11
#1020000
b101100 9
01
#1030000
b10101 &
b10101 U
b101100 W
b101101 %
b101101 V
b11111 H
b11111 a
b100000 g
b100001 f
b101100 h
b10101 t
11
#1040000
b101101 9
01
#1050000
b100000 H
b100000 a
b100001 g
b100010 f
b101101 h
b10110 &
b10110 U
b101101 W
b101110 %
b101110 V
b10101 t
11
#1060000
b101110 9
01
#1070000
b10111 &
b10111 U
b101110 W
b101111 %
b101111 V
b100001 H
b100001 a
b100010 g
b100011 f
b101110 h
b10101 t
11
#1080000
b101111 9
01
#1090000
b100010 H
b100010 a
b100011 g
b100100 f
b101111 h
b11000 &
b11000 U
b101111 W
b110000 %
b110000 V
b10101 t
11
#1100000
b110000 9
01
#1110000
b11001 &
b11001 U
b110000 W
b110001 %
b110001 V
b100011 H
b100011 a
b100100 g
b100101 f
b110000 h
b10101 t
11
#1120000
b110001 9
01
#1130000
b100100 H
b100100 a
b100101 g
b100110 f
b110001 h
b11010 &
b11010 U
b110001 W
b110010 %
b110010 V
b10101 t
11
#1140000
b110010 9
01
#1150000
b11011 &
b11011 U
b110010 W
b110011 %
b110011 V
b100101 H
b100101 a
b100110 g
b100111 f
b110010 h
b10101 t
11
#1160000
b110011 9
01
#1170000
b100110 H
b100110 a
b100111 g
b101000 f
b110011 h
b11100 &
b11100 U
b110011 W
b110100 %
b110100 V
b10101 t
11
#1180000
b110100 9
01
#1190000
b11101 &
b11101 U
b110100 W
b110101 %
b110101 V
b100111 H
b100111 a
b101000 g
b101001 f
b110100 h
b10101 t
11
#1200000
b110101 9
01
#1210000
b101000 H
b101000 a
b101001 g
b101010 f
b110101 h
b11110 &
b11110 U
b110101 W
b110110 %
b110110 V
b10101 t
11
#1220000
b110110 9
01
#1230000
b11111 &
b11111 U
b110110 W
b110111 %
b110111 V
b101001 H
b101001 a
b101010 g
b101011 f
b110110 h
b10101 t
11
#1240000
b110111 9
01
#1250000
b101010 H
b101010 a
b101011 g
b101100 f
b110111 h
b100000 &
b100000 U
b110111 W
b111000 %
b111000 V
b10101 t
11
#1260000
b111000 9
01
#1270000
b100001 &
b100001 U
b111000 W
b111001 %
b111001 V
b101011 H
b101011 a
b101100 g
b101101 f
b111000 h
b10101 t
11
#1280000
b111001 9
01
#1290000
b101100 H
b101100 a
b101101 g
b101110 f
b111001 h
b100010 &
b100010 U
b111001 W
b111010 %
b111010 V
b10101 t
11
#1300000
b111010 9
01
#1310000
b100011 &
b100011 U
b111010 W
b111011 %
b111011 V
b101101 H
b101101 a
b101110 g
b101111 f
b111010 h
b10101 t
11
#1320000
b111011 9
01
#1330000
b101110 H
b101110 a
b101111 g
b110000 f
b111011 h
b100100 &
b100100 U
b111011 W
b111100 %
b111100 V
b10101 t
11
#1340000
b111100 9
01
#1350000
b100101 &
b100101 U
b111100 W
b111101 %
b111101 V
b101111 H
b101111 a
b110000 g
b110001 f
b111100 h
b10101 t
11
#1360000
b111101 9
01
#1370000
b110000 H
b110000 a
b110001 g
b110010 f
b111101 h
b100110 &
b100110 U
b111101 W
b111110 %
b111110 V
b10101 t
11
#1380000
b111110 9
01
#1390000
b100111 &
b100111 U
b111110 W
b111111 %
b111111 V
b110001 H
b110001 a
b110010 g
b110011 f
b111110 h
b10101 t
11
#1400000
b111111 9
01
#1410000
b110010 H
b110010 a
b110011 g
b110100 f
b111111 h
b101000 &
b101000 U
b111111 W
b1000000 %
b1000000 V
b10101 t
11
#1420000
b1000000 9
01
#1430000
b101001 &
b101001 U
b1000000 W
b1000001 %
b1000001 V
b110011 H
b110011 a
b110100 g
b110101 f
b1000000 h
b10101 t
11
#1440000
b1000001 9
01
#1450000
b110100 H
b110100 a
b110101 g
b110110 f
b1000001 h
b101010 &
b101010 U
b1000001 W
b1000010 %
b1000010 V
b10101 t
11
#1460000
b1000010 9
01
#1470000
b101011 &
b101011 U
b1000010 W
b1000011 %
b1000011 V
b110101 H
b110101 a
b110110 g
b110111 f
b1000010 h
b10101 t
11
#1480000
b1000011 9
01
#1490000
b110110 H
b110110 a
b110111 g
b111000 f
b1000011 h
b101100 &
b101100 U
b1000011 W
b1000100 %
b1000100 V
b10101 t
11
#1500000
b1000100 9
01
#1510000
b101101 &
b101101 U
b1000100 W
b1000101 %
b1000101 V
b110111 H
b110111 a
b111000 g
b111001 f
b1000100 h
b10101 t
11
#1520000
b1000101 9
01
#1530000
b111000 H
b111000 a
b111001 g
b111010 f
b1000101 h
b101110 &
b101110 U
b1000101 W
b1000110 %
b1000110 V
b10101 t
11
#1540000
b1000110 9
01
#1550000
b101111 &
b101111 U
b1000110 W
b1000111 %
b1000111 V
b111001 H
b111001 a
b111010 g
b111011 f
b1000110 h
b10101 t
11
#1560000
b1000111 9
01
#1570000
b111010 H
b111010 a
b111011 g
b111100 f
b1000111 h
b110000 &
b110000 U
b1000111 W
b1001000 %
b1001000 V
b10101 t
11
#1580000
b1001000 9
01
#1590000
b110001 &
b110001 U
b1001000 W
b1001001 %
b1001001 V
b111011 H
b111011 a
b111100 g
b111101 f
b1001000 h
b10101 t
11
#1600000
b1001001 9
01
#1610000
b111100 H
b111100 a
b111101 g
b111110 f
b1001001 h
b110010 &
b110010 U
b1001001 W
b1001010 %
b1001010 V
b10101 t
11
#1620000
b1001010 9
01
#1630000
b110011 &
b110011 U
b1001010 W
b1001011 %
b1001011 V
b111101 H
b111101 a
b111110 g
b111111 f
b1001010 h
b10101 t
11
#1640000
b1001011 9
01
#1650000
b111110 H
b111110 a
b111111 g
b1000000 f
b1001011 h
b110100 &
b110100 U
b1001011 W
b1001100 %
b1001100 V
b10101 t
11
#1660000
b1001100 9
01
#1670000
b110101 &
b110101 U
b1001100 W
b1001101 %
b1001101 V
b111111 H
b111111 a
b1000000 g
b1000001 f
b1001100 h
b10101 t
11
#1680000
b1001101 9
01
#1690000
b1000000 H
b1000000 a
b1000001 g
b1000010 f
b1001101 h
b110110 &
b110110 U
b1001101 W
b1001110 %
b1001110 V
b10101 t
11
#1700000
b1001110 9
01
#1710000
b110111 &
b110111 U
b1001110 W
b1001111 %
b1001111 V
b1000001 H
b1000001 a
b1000010 g
b1000011 f
b1001110 h
b10101 t
11
#1720000
b1001111 9
01
#1730000
b1000010 H
b1000010 a
b1000011 g
b1000100 f
b1001111 h
b111000 &
b111000 U
b1001111 W
b1010000 %
b1010000 V
b10101 t
11
#1740000
b1010000 9
01
#1750000
b111001 &
b111001 U
b1010000 W
b1010001 %
b1010001 V
b1000011 H
b1000011 a
b1000100 g
b1000101 f
b1010000 h
b10101 t
11
#1760000
b1010001 9
01
#1770000
b1000100 H
b1000100 a
b1000101 g
b1000110 f
b1010001 h
b111010 &
b111010 U
b1010001 W
b1010010 %
b1010010 V
b10101 t
11
#1780000
b1010010 9
01
