Experiment-5-Advanced/RTL/bnn_folded.sv
`timescale 1ns/1ps
module bnn_folded(
 input logic clk,rst,accept,input logic [15:0] x,sample_id,model_id,
 input logic [255:0] hw,input logic [63:0] ow,input logic [79:0] thresholds,input logic [31:0] biases,
 output logic busy,valid,output logic [35:0] scores,output logic [15:0] hidden,out_sample,out_model,
 output logic [1:0] out_class,output logic [8:0] margin
);
 import bnn_math_pkg::*;
 logic [4:0] step; logic [15:0] xr; logic [10:0] dec;
 logic [15:0] selected_w;logic [4:0] pc;
 always_comb begin
   selected_w=0;
   if(step<16) selected_w=hw[step*16+:16];
   else if(step<20) selected_w=ow[(step-16)*16+:16];
 end
 assign pc=pop16(~((step<16 ? xr : hidden)^selected_w));
 assign dec=decide(scores);
 always_ff @(posedge clk) begin
   if(rst) begin
     step<=0;xr<=0;busy<=0;valid<=0;scores<=0;hidden<=0;out_sample<=0;out_model<=0;out_class<=3;margin<=0;
   end else begin
     valid<=0;
     if(accept&&!busy) begin
       xr<=x;out_sample<=sample_id;out_model<=model_id;busy<=1;step<=0;hidden<=0;
     end else if(busy) begin
       step<=step+1'b1;
       if(step<16) hidden[step[3:0]]<=pc>=thresholds[step*5+:5];
       else if(step<20) scores[(step-16)*9+:9]<=score16(pc,biases[(step-16)*8+:8]);
       else begin valid<=1;busy<=0;out_class<=dec[1:0];margin<=dec[10:2];end
     end
   end
 end
endmodule

Experiment-5-Advanced/RTL/bnn_parallel.sv
`timescale 1ns/1ps
module bnn_parallel(
 input logic clk,rst,accept,input logic [15:0] x,sample_id,model_id,
 input logic [255:0] hw,input logic [63:0] ow,input logic [79:0] thresholds,input logic [31:0] biases,
 output logic busy,pre_valid,output logic [35:0] pre_scores,output logic [15:0] pre_hidden,pre_sample,pre_model,
 output logic [1:0] pre_class,output logic [8:0] pre_margin,
 output logic valid,output logic [35:0] scores,output logic [15:0] hidden,out_sample,out_model,
 output logic [1:0] out_class,output logic [8:0] margin
);
 import bnn_math_pkg::*;
 logic [4:0] v; logic [15:0] xr,h2,h3,h4;
 logic [79:0] hp; logic [19:0] op;
 logic [15:0] sid[0:4],mid[0:4]; logic [10:0] dec;
 assign busy=|v; assign pre_valid=v[4]; assign pre_hidden=h4;
 assign pre_sample=sid[4]; assign pre_model=mid[4];
 assign dec=decide(pre_scores); assign pre_class=dec[1:0]; assign pre_margin=dec[10:2];
 always_ff @(posedge clk) begin
   if(rst) begin
     v<=0; valid<=0; xr<=0; hp<=0; h2<=0; h3<=0; h4<=0; op<=0; pre_scores<=0;
     scores<=0; hidden<=0; out_sample<=0; out_model<=0; out_class<=3; margin<=0;
     for(int i=0;i<5;i++) begin sid[i]<=0;mid[i]<=0;end
   end else begin
     v<={v[3:0],accept}; valid<=v[4];
     if(accept) begin xr<=x;sid[0]<=sample_id;mid[0]<=model_id;end
     for(int i=1;i<5;i++) begin sid[i]<=sid[i-1];mid[i]<=mid[i-1];end
     if(v[0]) for(int i=0;i<16;i++) hp[i*5+:5]<=pop16(~(xr^hw[i*16+:16]));
     if(v[1]) for(int i=0;i<16;i++) h2[i]<=hp[i*5+:5]>=thresholds[i*5+:5];
     if(v[2]) begin
       h3<=h2;
       for(int i=0;i<4;i++) op[i*5+:5]<=pop16(~(h2^ow[i*16+:16]));
     end
     if(v[3]) begin
       h4<=h3;
       for(int i=0;i<4;i++) pre_scores[i*9+:9]<=score16(op[i*5+:5],biases[i*8+:8]);
     end
     if(v[4]) begin
       scores<=pre_scores;hidden<=h4;out_sample<=sid[4];out_model<=mid[4];
       out_class<=pre_class;margin<=pre_margin;
     end
   end
 end
endmodule

Experiment-5-Advanced/Testbench/tb_waveform.sv
`timescale 1ns/1ps
module tb_waveform;
 parameter PASS_FILE="CORE_TEST_PASS.txt";
 parameter DATA_DIR=".";
 import bnn_math_pkg::*;
 logic clk=0;always #10 clk=~clk;
 logic rst=1,pa=0,sa=0;logic [15:0] x=0,sid=0,mid=1;
 logic [255:0] hw;logic [63:0] ow;logic [79:0] ts;logic [31:0] bs;
 logic pb,pv,prv,sb,sv;logic [35:0] psc,prsc,ssc;logic [15:0] ph,prh,sh,ps,prs,ss,pm,prm,sm;
 logic [1:0] pc,prc,sc;logic [8:0] pmar,prmar,smar;
 logic [79:0] golden[0:65535];logic [15:0] words[0:41];
 integer cycle=0,phase=0,stream_count=0,total_folded=0;integer stamps[0:65535];
 bnn_parallel p(.clk,.rst,.accept(pa),.x,.sample_id(sid),.model_id(mid),.hw,.ow,.thresholds(ts),.biases(bs),
 .busy(pb),.pre_valid(prv),.pre_scores(prsc),.pre_hidden(prh),.pre_sample(prs),.pre_model(prm),.pre_class(prc),.pre_margin(prmar),
 .valid(pv),.scores(psc),.hidden(ph),.out_sample(ps),.out_model(pm),.out_class(pc),.margin(pmar));
 bnn_folded s(.clk,.rst,.accept(sa),.x,.sample_id(sid),.model_id(mid),.hw,.ow,.thresholds(ts),.biases(bs),
 .busy(sb),.valid(sv),.scores(ssc),.hidden(sh),.out_sample(ss),.out_model(sm),.out_class(sc),.margin(smar));

 logic [15:0] raw_case=0;
 logic [15:0] raw_cases[0:5];
 integer fd;
 always @(posedge clk) cycle=cycle+1;
 task check(input bit okay,input string msg);
   if(!okay) $fatal(1,"WAVEFORM FAIL: %s at cycle %0d",msg,cycle);
 endtask
 initial begin : trace
   integer stamp; time accept_time,p_time,f_time;
   $timeformat(-9,0,"",0);
   $dumpfile("waveform.vcd");
   $dumpvars(0,clk,rst,pa,sa,raw_case,x,mid,pv,sv,pc,sc,pm,sm,psc,ssc,pb,sb);
   fd=$fopen("waveform_measurements.csv","w");
   $fdisplay(fd,"profile,raw_hex,encoded_hex,model_id,accept_ns,parallel_valid_ns,folded_valid_ns,parallel_class,folded_class,parallel_cycles,folded_cycles");
   raw_cases[0]=16'h0000;raw_cases[1]=16'h0111;raw_cases[2]=16'h0222;
   raw_cases[3]=16'h0233;raw_cases[4]=16'h2233;raw_cases[5]=16'h0024;
   hw=0;ow=0;ts=0;bs=0;
   for(int profile=0;profile<2;profile++) begin
     rst=1;pa=0;sa=0;repeat(3) @(negedge clk);
     if(profile==0) begin
       $readmemh({DATA_DIR,"/Models/normal.mem"},words);
       $readmemh({DATA_DIR,"/Data/normal_golden.mem"},golden);
     end else begin
       $readmemh({DATA_DIR,"/Models/cautious.mem"},words);
       $readmemh({DATA_DIR,"/Data/cautious_golden.mem"},golden);
     end
     for(int j=0;j<16;j++) begin hw[j*16+:16]=words[j];ts[j*5+:5]=words[20+j][4:0];end
     for(int j=0;j<4;j++) begin ow[j*16+:16]=words[16+j];bs[j*8+:8]=words[36+j][7:0];end
     mid=words[40];rst=0;
     for(int k=0;k<6;k++) begin
       @(negedge clk);raw_case=raw_cases[k];x=encode_raw(raw_case);sid=16'(k);pa=1;sa=1;
       @(posedge clk);#2;stamp=cycle;accept_time=$time;
       @(negedge clk);pa=0;sa=0;
       for(int n=1;n<=21;n++) begin
         @(posedge clk);#2;
         check(pv===(n==5),"parallel exact valid pulse");
         check(sv===(n==21),"folded exact valid pulse");
         if(n==5) begin
           p_time=$time;
           check({1'b0,x,ph,psc,pmar,pc}===golden[x],"parallel golden match");
           check(pm==mid&&cycle-stamp==5,"parallel tag and latency");
         end
         if(n==21) begin
           f_time=$time;
           check({1'b0,x,sh,ssc,smar,sc}===golden[x],"folded golden match");
           check(sm==mid&&cycle-stamp==21,"folded tag and latency");
         end
       end
       $fdisplay(fd,"%s,%04x,%04x,%0d,%0t,%0t,%0t,%0d,%0d,5,21",profile==0?"normal":"cautious",raw_case,x,mid,accept_time,p_time,f_time,pc,sc);
       $display("TRACE PASS profile=%0d raw=%04x class=%0d/%0d cycles=5/21",profile,raw_case,pc,sc);
       repeat(3) @(negedge clk);
     end
   end
   $fclose(fd);$display("WAVEFORM TRACE PASS: 12 cases, independent golden matches, model tags, exact 5/21-cycle latency.");$finish;
 end
endmodule

Experiment-5-Advanced/Simulation/waveform.vcd
$date
	Thu Oct  8 17:32:42 2026
$end
$version
	Icarus Verilog
$end
$timescale
	1ps
$end
$scope module tb_waveform $end
$var reg 1 ! clk $end
$upscope $end
$scope module tb_waveform $end
$var reg 1 " rst $end
$upscope $end
$scope module tb_waveform $end
$var reg 1 # pa $end
$upscope $end
$scope module tb_waveform $end
$var reg 1 $ sa $end
$upscope $end
$scope module tb_waveform $end
$var reg 16 % raw_case [15:0] $end
$upscope $end
$scope module tb_waveform $end
$var reg 16 & x [15:0] $end
$upscope $end
$scope module tb_waveform $end
$var reg 16 ' mid [15:0] $end
$upscope $end
$scope module tb_waveform $end
$var wire 1 ( pv $end
$upscope $end
$scope module tb_waveform $end
$var wire 1 ) sv $end
$upscope $end
$scope module tb_waveform $end
$var wire 2 * pc [1:0] $end
$upscope $end
$scope module tb_waveform $end
$var wire 2 + sc [1:0] $end
$upscope $end
$scope module tb_waveform $end
$var wire 16 , pm [15:0] $end
$upscope $end
$scope module tb_waveform $end
$var wire 16 - sm [15:0] $end
$upscope $end
$scope module tb_waveform $end
$var wire 36 . psc [35:0] $end
$upscope $end
$scope module tb_waveform $end
$var wire 36 / ssc [35:0] $end
$upscope $end
$scope module tb_waveform $end
$var wire 1 0 pb $end
$upscope $end
$scope module tb_waveform $end
$var wire 1 1 sb $end
$upscope $end
$enddefinitions $end
$comment Show the parameter values. $end
$dumpall
$end
#0
$dumpvars
x1
x0
bx /
bx .
bx -
bx ,
bx +
bx *
x)
x(
b1 '
b0 &
b0 %
0$
0#
1"
0!
$end
#10000
b11 *
b0 ,
b0 .
0(
00
b11 +
b0 -
b0 /
0)
01
1!
#20000
0!
#30000
1!
#40000
0!
#50000
1!
#60000
0"
0!
#70000
1!
#80000
1$
1#
0!
#90000
11
b1 -
10
1!
#100000
0$
0#
0!
#110000
1!
#120000
0!
#130000
1!
#140000
0!
#150000
1!
#160000
0!
#170000
1!
#180000
0!
#190000
b0 *
b1 ,
b111110111111110011111111101000000110 .
1(
00
1!
#200000
0!
#210000
0(
1!
#220000
0!
#230000
1!
#240000
0!
#250000
1!
#260000
0!
#270000
1!
#280000
0!
#290000
1!
#300000
0!
#310000
1!
#320000
0!
#330000
1!
#340000
0!
#350000
1!
#360000
0!
#370000
1!
#380000
0!
#390000
1!
#400000
0!
#410000
1!
#420000
0!
#430000
b110 /
1!
#440000
0!
#450000
b111111101000000110 /
1!
#460000
0!
#470000
b111110011111111101000000110 /
1!
#480000
0!
#490000
b111110111111110011111111101000000110 /
1!
#500000
0!
#510000
b0 +
01
1)
1!
#520000
0!
#530000
0)
1!
#540000
0!
#550000
1!
#560000
0!
#570000
1!
#580000
1$
1#
b100010001 &
b100010001 %
0!
#590000
11
10
1!
#600000
0$
0#
0!
#610000
1!
#620000
0!
#630000
1!
#640000
0!
#650000
1!
#660000
0!
#670000
1!
#680000
0!
#690000
1(
00
1!
#700000
0!
#710000
0(
1!
#720000
0!
#730000
1!
#740000
0!
#750000
1!
#760000
0!
#770000
1!
#780000
0!
#790000
1!
#800000
0!
#810000
1!
#820000
0!
#830000
1!
#840000
0!
#850000
1!
#860000
0!
#870000
1!
#880000
0!
#890000
1!
#900000
0!
#910000
1!
#920000
0!
#930000
1!
#940000
0!
#950000
1!
#960000
0!
#970000
1!
#980000
0!
#990000
1!
#1000000
0!
#1010000
01
1)
1!
#1020000
0!
#1030000
0)
1!
#1040000
0!
#1050000
1!
#1060000
0!
#1070000
1!
#1080000
1$
1#
b1100110011 &
b1000100010 %
0!
#1090000
11
10
1!
#1100000
0$
0#
0!
#1110000
1!
#1120000
0!
#1130000
1!
#1140000
0!
#1150000
1!
#1160000
0!
#1170000
1!
#1180000
0!
#1190000
b1 *
b111110001111111101000000111111111100 .
1(
00
1!
#1200000
0!
#1210000
0(
1!
#1220000
0!
#1230000
1!
#1240000
0!
#1250000
1!
#1260000
0!
#1270000
1!
#1280000
0!
#1290000
1!
#1300000
0!
#1310000
1!
#1320000
0!
#1330000
1!
#1340000
0!
#1350000
1!
#1360000
0!
#1370000
1!
#1380000
0!
#1390000
1!
#1400000
0!
#1410000
1!
#1420000
0!
#1430000
b111110111111110011111111101111111100 /
1!
#1440000
0!
#1450000
b111110111111110011000000111111111100 /
1!
#1460000
0!
#1470000
b111110111111111101000000111111111100 /
1!
#1480000
0!
#1490000
b111110001111111101000000111111111100 /
1!
#1500000
0!
#1510000
b1 +
01
1)
1!
#1520000
0!
#1530000
0)
1!
#1540000
0!
#1550000
1!
#1560000
0!
#1570000
1!
#1580000
1$
1#
b1101110111 &
b1000110011 %
0!
#1590000
11
10
1!
#1600000
0$
0#
0!
#1610000
1!
#1620000
0!
#1630000
1!
#1640000
0!
#1650000
1!
#1660000
0!
#1670000
1!
#1680000
0!
#1690000
b10 *
b111111011000000111111111101111110010 .
1(
00
1!
#1700000
0!
#1710000
0(
1!
#1720000
0!
#1730000
1!
#1740000
0!
#1750000
1!
#1760000
0!
#1770000
1!
#1780000
0!
#1790000
1!
#1800000
0!
#1810000
1!
#1820000
0!
#1830000
1!
#1840000
0!
#1850000
1!
#1860000
0!
#1870000
1!
#1880000
0!
#1890000
1!
#1900000
0!
#1910000
1!
#1920000
0!
#1930000
b111110001111111101000000111111110010 /
1!
#1940000
0!
#1950000
b111110001111111101111111101111110010 /
1!
#1960000
0!
#1970000
b111110001000000111111111101111110010 /
1!
#1980000
0!
#1990000
b111111011000000111111111101111110010 /
1!
#2000000
0!
#2010000
b10 +
01
1)
1!
#2020000
0!
#2030000
0)
1!
#2040000
0!
#2050000
1!
#2060000
0!
#2070000
1!
#2080000
1$
1#
b11001101110111 &
b10001000110011 %
0!
#2090000
11
10
1!
#2100000
0$
0#
0!
#2110000
1!
#2120000
0!
#2130000
1!
#2140000
0!
#2150000
1!
#2160000
0!
#2170000
1!
#2180000
0!
#2190000
b11 *
b111111111011111110001111110010 .
1(
00
1!
#2200000
0!
#2210000
0(
1!
#2220000
0!
#2230000
1!
#2240000
0!
#2250000
1!
#2260000
0!
#2270000
1!
#2280000
0!
#2290000
1!
#2300000
0!
#2310000
1!
#2320000
0!
#2330000
1!
#2340000
0!
#2350000
1!
#2360000
0!
#2370000
1!
#2380000
0!
#2390000
1!
#2400000
0!
#2410000
1!
#2420000
0!
#2430000
1!
#2440000
0!
#2450000
b111111011000000111111110001111110010 /
1!
#2460000
0!
#2470000
b111111011111111011111110001111110010 /
1!
#2480000
0!
#2490000
b111111111011111110001111110010 /
1!
#2500000
0!
#2510000
b11 +
01
1)
1!
#2520000
0!
#2530000
0)
1!
#2540000
0!
#2550000
1!
#2560000
0!
#2570000
1!
#2580000
1$
1#
b111111 &
b100100 %
0!
#2590000
11
10
1!
#2600000
0$
0#
0!
#2610000
1!
#2620000
0!
#2630000
1!
#2640000
0!
#2650000
1!
#2660000
0!
#2670000
1!
#2680000
0!
#2690000
b1 *
b111110001111111101000000111111111100 .
1(
00
1!
#2700000
0!
#2710000
0(
1!
#2720000
0!
#2730000
1!
#2740000
0!
#2750000
1!
#2760000
0!
#2770000
1!
#2780000
0!
#2790000
1!
#2800000
0!
#2810000
1!
#2820000
0!
#2830000
1!
#2840000
0!
#2850000
1!
#2860000
0!
#2870000
1!
#2880000
0!
#2890000
1!
#2900000
0!
#2910000
1!
#2920000
0!
#2930000
b111111111011111110001111111100 /
1!
#2940000
0!
#2950000
b111111111011000000111111111100 /
1!
#2960000
0!
#2970000
b111111111101000000111111111100 /
1!
#2980000
0!
#2990000
b111110001111111101000000111111111100 /
1!
#3000000
0!
#3010000
b1 +
01
1)
1!
#3020000
0!
#3030000
0)
1!
#3040000
0!
#3050000
1!
#3060000
1"
0!
#3070000
b11 +
b0 -
b0 /
b11 *
b0 ,
b0 .
1!
#3080000
0!
#3090000
1!
#3100000
0!
#3110000
1!
#3120000
0"
b10 '
0!
#3130000
1!
#3140000
1$
1#
b0 &
b0 %
0!
#3150000
11
b10 -
10
1!
#3160000
0$
0#
0!
#3170000
1!
#3180000
0!
#3190000
1!
#3200000
0!
#3210000
1!
#3220000
0!
#3230000
1!
#3240000
0!
#3250000
b0 *
b10 ,
b111110001111111101000001000000001110 .
1(
00
1!
#3260000
0!
#3270000
0(
1!
#3280000
0!
#3290000
1!
#3300000
0!
#3310000
1!
#3320000
0!
#3330000
1!
#3340000
0!
#3350000
1!
#3360000
0!
#3370000
1!
#3380000
0!
#3390000
1!
#3400000
0!
#3410000
1!
#3420000
0!
#3430000
1!
#3440000
0!
#3450000
1!
#3460000
0!
#3470000
1!
#3480000
0!
#3490000
b1110 /
1!
#3500000
0!
#3510000
b1000000001110 /
1!
#3520000
0!
#3530000
b111111101000001000000001110 /
1!
#3540000
0!
#3550000
b111110001111111101000001000000001110 /
1!
#3560000
0!
#3570000
b0 +
01
1)
1!
#3580000
0!
#3590000
0)
1!
#3600000
0!
#3610000
1!
#3620000
0!
#3630000
1!
#3640000
1$
1#
b100010001 &
b100010001 %
0!
#3650000
11
10
1!
#3660000
0$
0#
0!
#3670000
1!
#3680000
0!
#3690000
1!
#3700000
0!
#3710000
1!
#3720000
0!
#3730000
1!
#3740000
0!
#3750000
b1 *
b111111001000000101000010000000000110 .
1(
00
1!
#3760000
0!
#3770000
0(
1!
#3780000
0!
#3790000
1!
#3800000
0!
#3810000
1!
#3820000
0!
#3830000
1!
#3840000
0!
#3850000
1!
#3860000
0!
#3870000
1!
#3880000
0!
#3890000
1!
#3900000
0!
#3910000
1!
#3920000
0!
#3930000
1!
#3940000
0!
#3950000
1!
#3960000
0!
#3970000
1!
#3980000
0!
#3990000
b111110001111111101000001000000000110 /
1!
#4000000
0!
#4010000
b111110001111111101000010000000000110 /
1!
#4020000
0!
#4030000
b111110001000000101000010000000000110 /
1!
#4040000
0!
#4050000
b111111001000000101000010000000000110 /
1!
#4060000
0!
#4070000
b1 +
01
1)
1!
#4080000
0!
#4090000
0)
1!
#4100000
0!
#4110000
1!
#4120000
0!
#4130000
1!
#4140000
1$
1#
b1100110011 &
b1000100010 %
0!
#4150000
11
10
1!
#4160000
0$
0#
0!
#4170000
1!
#4180000
0!
#4190000
1!
#4200000
0!
#4210000
1!
#4220000
0!
#4230000
1!
#4240000
0!
#4250000
b10 *
b101000010001000000100111111010 .
1(
00
1!
#4260000
0!
#4270000
0(
1!
#4280000
0!
#4290000
1!
#4300000
0!
#4310000
1!
#4320000
0!
#4330000
1!
#4340000
0!
#4350000
1!
#4360000
0!
#4370000
1!
#4380000
0!
#4390000
1!
#4400000
0!
#4410000
1!
#4420000
0!
#4430000
1!
#4440000
0!
#4450000
1!
#4460000
0!
#4470000
1!
#4480000
0!
#4490000
b111111001000000101000010000111111010 /
1!
#4500000
0!
#4510000
b111111001000000101000000100111111010 /
1!
#4520000
0!
#4530000
b111111001000010001000000100111111010 /
1!
#4540000
0!
#4550000
b101000010001000000100111111010 /
1!
#4560000
0!
#4570000
b10 +
01
1)
1!
#4580000
0!
#4590000
0)
1!
#4600000
0!
#4610000
1!
#4620000
0!
#4630000
1!
#4640000
1$
1#
b1101110111 &
b1000110011 %
0!
#4650000
11
10
1!
#4660000
0$
0#
0!
#4670000
1!
#4680000
0!
#4690000
1!
#4700000
0!
#4710000
1!
#4720000
0!
#4730000
1!
#4740000
0!
#4750000
1(
00
1!
#4760000
0!
#4770000
0(
1!
#4780000
0!
#4790000
1!
#4800000
0!
#4810000
1!
#4820000
0!
#4830000
1!
#4840000
0!
#4850000
1!
#4860000
0!
#4870000
1!
#4880000
0!
#4890000
1!
#4900000
0!
#4910000
1!
#4920000
0!
#4930000
1!
#4940000
0!
#4950000
1!
#4960000
0!
#4970000
1!
#4980000
0!
#4990000
1!
#5000000
0!
#5010000
1!
#5020000
0!
#5030000
1!
#5040000
0!
#5050000
1!
#5060000
0!
#5070000
01
1)
1!
#5080000
0!
#5090000
0)
1!
#5100000
0!
#5110000
1!
#5120000
0!
#5130000
1!
#5140000
1$
1#
b11001101110111 &
b10001000110011 %
0!
#5150000
11
10
1!
#5160000
0$
0#
0!
#5170000
1!
#5180000
0!
#5190000
1!
#5200000
0!
#5210000
1!
#5220000
0!
#5230000
1!
#5240000
0!
#5250000
b11 *
b10001000000101111111000111101110 .
1(
00
1!
#5260000
0!
#5270000
0(
1!
#5280000
0!
#5290000
1!
#5300000
0!
#5310000
1!
#5320000
0!
#5330000
1!
#5340000
0!
#5350000
1!
#5360000
0!
#5370000
1!
#5380000
0!
#5390000
1!
#5400000
0!
#5410000
1!
#5420000
0!
#5430000
1!
#5440000
0!
#5450000
1!
#5460000
0!
#5470000
1!
#5480000
0!
#5490000
b101000010001000000100111101110 /
1!
#5500000
0!
#5510000
b101000010001111111000111101110 /
1!
#5520000
0!
#5530000
b101000000101111111000111101110 /
1!
#5540000
0!
#5550000
b10001000000101111111000111101110 /
1!
#5560000
0!
#5570000
b11 +
01
1)
1!
#5580000
0!
#5590000
0)
1!
#5600000
0!
#5610000
1!
#5620000
0!
#5630000
1!
#5640000
1$
1#
b111111 &
b100100 %
0!
#5650000
11
10
1!
#5660000
0$
0#
0!
#5670000
1!
#5680000
0!
#5690000
1!
#5700000
0!
#5710000
1!
#5720000
0!
#5730000
1!
#5740000
0!
#5750000
b10 *
b101000010001000000100111111010 .
1(
00
1!
#5760000
0!
#5770000
0(
1!
#5780000
0!
#5790000
1!
#5800000
0!
#5810000
1!
#5820000
0!
#5830000
1!
#5840000
0!
#5850000
1!
#5860000
0!
#5870000
1!
#5880000
0!
#5890000
1!
#5900000
0!
#5910000
1!
#5920000
0!
#5930000
1!
#5940000
0!
#5950000
1!
#5960000
0!
#5970000
1!
#5980000
0!
#5990000
b10001000000101111111000111111010 /
1!
#6000000
0!
#6010000
b10001000000101000000100111111010 /
1!
#6020000
0!
#6030000
b10001000010001000000100111111010 /
1!
#6040000
0!
#6050000
b101000010001000000100111111010 /
1!
#6060000
0!
#6070000
b10 +
01
1)
1!
#6080000
0!
#6090000
0)
1!
